<?xml version="1.0" encoding="UTF-8"?><slideShow>
    <setUpMaster>
    <textBgColor>000000</textBgColor>
    <hedColor>fff600</hedColor>
    <deckColor>ffffff</deckColor>
    <watchColor>fff600</watchColor>
    <readColor>fff600</readColor>
    <otherColor></otherColor>
    <indicatorColor>fff600</indicatorColor>
    <thumbColor>000000</thumbColor>
  </setUpMaster>
       <slide>
    <id>420</id>
    <slideSetUP>
      <isVertBG>false</isVertBG>
      <textBgSlideColor></textBgSlideColor>
      <hedSlideColor></hedSlideColor>
      <deckSlideColor></deckSlideColor>
      <watchSlideColor>ffffff</watchSlideColor>
      <readSlideColor></readSlideColor>
      <otherSlideColor></otherSlideColor>
      <slideThumbBorderColor></slideThumbBorderColor>
    </slideSetUP>
    <imageURI>images/darksiders_010610.jpg</imageURI>
    <thumbURI>images/darksiders_010610t.jpg</thumbURI>
    <clickURI>images/darksiders_010610.jpg</clickURI>
    <titleGoToURI>images/darksiders_010610.jpg</titleGoToURI> 
    <subtitleGoToURI>images/darksiders_010610.jpg</subtitleGoToURI> 
    <imageGoToURI>images/darksiders_010610.jpg</imageGoToURI>
    <thumbGoToURI>images/darksiders_010610.jpg</thumbGoToURI>
    <title>Quality of Service</title>
    <subTitle>Dedicated service, excellent quality</subTitle>
    <watchButton>
      <watchTitle>Watch</watchTitle>
      <watchIcon>watchIcon</watchIcon>
      <watchURI>images/darksiders_010610.jpg</watchURI>
    </watchButton>
    <readButton>
      <readTitle></readTitle>
      <readIcon>readIcon</readIcon>
      <readURI></readURI>
    </readButton>
    <otherButton>
      <otherTitle></otherTitle>
      <otherIcon></otherIcon>
      <otherURI></otherURI>
      <otherIconURI></otherIconURI>
    </otherButton>
  </slide>
      <slide>
    <id>420</id>
    <slideSetUP>
      <isVertBG>false</isVertBG>
      <textBgSlideColor></textBgSlideColor>
      <hedSlideColor></hedSlideColor>
      <deckSlideColor></deckSlideColor>
      <watchSlideColor></watchSlideColor>
      <readSlideColor></readSlideColor>
      <otherSlideColor></otherSlideColor>
      <slideThumbBorderColor></slideThumbBorderColor>
    </slideSetUP>
    <imageURI>images/ces_010610.jpg</imageURI>
    <thumbURI>images/ces_010610t.jpg</thumbURI>
    <clickURI>images/ces_010610.jpg</clickURI>
    <titleGoToURI>images/ces_010610.jpg</titleGoToURI> 
    <subtitleGoToURI>images/ces_010610.jpg</subtitleGoToURI> 
    <imageGoToURI>images/ces_010610.jpg</imageGoToURI>
    <thumbGoToURI>images/ces_010610.jpg</thumbGoToURI>
    <title>Factory scene</title>
    <subTitle>Advanced equipment, exquisite technology, creating Pula En Green Pipe</subTitle>
    <watchButton>
      <watchTitle></watchTitle>
      <watchIcon>watchIcon</watchIcon>
      <watchURI>images/ces_010610.jpg</watchURI>
    </watchButton>
    <readButton>
      <readTitle></readTitle>
      <readIcon>readIcon</readIcon>
      <readURI></readURI>
    </readButton>
    <otherButton>
      <otherTitle></otherTitle>
      <otherIcon></otherIcon>
      <otherURI></otherURI>
      <otherIconURI></otherIconURI>
    </otherButton>
  </slide>
      <slide>
    <id>420</id>
    <slideSetUP>
      <isVertBG>false</isVertBG>
      <textBgSlideColor></textBgSlideColor>
      <hedSlideColor></hedSlideColor>
      <deckSlideColor></deckSlideColor>
      <watchSlideColor></watchSlideColor>
      <readSlideColor></readSlideColor>
      <otherSlideColor></otherSlideColor>
      <slideThumbBorderColor></slideThumbBorderColor>
    </slideSetUP>
    <imageURI>images/tots_010510.jpg</imageURI>
    <thumbURI>images/tots_010510t.jpg</thumbURI>
    <clickURI>images/tots_010510.jpg</clickURI>
    <titleGoToURI>images/tots_010510.jpg</titleGoToURI> 
    <subtitleGoToURI>images/tots_010510.jpg</subtitleGoToURI> 
    <imageGoToURI>images/tots_010510.jpg</imageGoToURI>
    <thumbGoToURI>images/tots_010510.jpg</thumbGoToURI>
    <title>Factory scene</title>
    <subTitle>Advanced equipment, exquisite technology, creating Pula En Green Pipe</subTitle>
    <watchButton>
      <watchTitle></watchTitle>
      <watchIcon>watchIcon</watchIcon>
      <watchURI>images/tots_010510.jpg</watchURI>
    </watchButton>
    <readButton>
      <readTitle></readTitle>
      <readIcon>readIcon</readIcon>
      <readURI></readURI>
    </readButton>
    <otherButton>
      <otherTitle></otherTitle>
      <otherIcon></otherIcon>
      <otherURI></otherURI>
      <otherIconURI></otherIconURI>
    </otherButton>
  </slide>
      <slide>
    <id>420</id>
    <slideSetUP>
      <isVertBG>false</isVertBG>
      <textBgSlideColor></textBgSlideColor>
      <hedSlideColor></hedSlideColor>
      <deckSlideColor></deckSlideColor>
      <watchSlideColor>ffffff</watchSlideColor>
      <readSlideColor></readSlideColor>
      <otherSlideColor></otherSlideColor>
      <slideThumbBorderColor></slideThumbBorderColor>
    </slideSetUP>
    <imageURI>images/bayonetta_010410.jpg</imageURI>
    <thumbURI>images/bayonetta_010410t.jpg</thumbURI>
    <clickURI>http://sc.xvna.com/</clickURI>
    <titleGoToURI>images/bayonetta_010410.jpg</titleGoToURI> 
    <subtitleGoToURI>images/bayonetta_010410.jpg</subtitleGoToURI> 
    <imageGoToURI>images/bayonetta_010410.jpg</imageGoToURI>
    <thumbGoToURI>images/bayonetta_010410.jpg</thumbGoToURI>
    <title>Staff photo</title>
    <subTitle>Energetic team of employees, to create a quality of life</subTitle>
    <watchButton>
      <watchTitle>Watch</watchTitle>
      <watchIcon>watchIcon</watchIcon>
      <watchURI>images/bayonetta_010410.jpg</watchURI>
    </watchButton>
    <readButton>
      <readTitle></readTitle>
      <readIcon>readIcon</readIcon>
      <readURI></readURI>
    </readButton>
    <otherButton>
      <otherTitle></otherTitle>
      <otherIcon></otherIcon>
      <otherURI></otherURI>
      <otherIconURI></otherIconURI>
    </otherButton>
  </slide>
      <slide>
    <id>420</id>
    <slideSetUP>
      <isVertBG>false</isVertBG>
      <textBgSlideColor></textBgSlideColor>
      <hedSlideColor></hedSlideColor>
      <deckSlideColor></deckSlideColor>
      <watchSlideColor>ffffff</watchSlideColor>
      <readSlideColor></readSlideColor>
      <otherSlideColor></otherSlideColor>
      <slideThumbBorderColor></slideThumbBorderColor>
    </slideSetUP>
    <imageURI>images/tvc_010510.jpg</imageURI>
    <thumbURI>images/tvc_010510t.jpg</thumbURI>
    <clickURI>images/tvc_010510.jpg</clickURI>
    <titleGoToURI>images/tvc_010510.jpg</titleGoToURI> 
    <subtitleGoToURI>images/tvc_010510.jpg</subtitleGoToURI> 
    <imageGoToURI>images/tvc_010510.jpg</imageGoToURI>
    <thumbGoToURI>images/tvc_010510.jpg</thumbGoToURI>
    <title>Factory scene</title>
    <subTitle>Advanced equipment, exquisite technology, creating Pula En Green Pipe</subTitle>
    <watchButton>
      <watchTitle>Watch</watchTitle>
      <watchIcon>watchIcon</watchIcon>
      <watchURI>images/tvc_010510.jpg</watchURI>
    </watchButton>
    <readButton>
      <readTitle></readTitle>
      <readIcon>readIcon</readIcon>
      <readURI></readURI>
    </readButton>
    <otherButton>
      <otherTitle></otherTitle>
      <otherIcon></otherIcon>
      <otherURI></otherURI>
      <otherIconURI></otherIconURI>
    </otherButton>
  </slide>
    </slideShow>